fileio_wrapper/__init__.py
fileio_wrapper/__version__.py
fileio_wrapper/fileio_wrapper.py
fileio_wrapper-1.0.3.dist-info/LICENSE
fileio_wrapper-1.0.3.dist-info/METADATA
fileio_wrapper-1.0.3.dist-info/WHEEL
fileio_wrapper-1.0.3.dist-info/top_level.txt
fileio_wrapper-1.0.3.dist-info/RECORD
