Metadata-Version: 2.1
Name: fileio-wrapper
Version: 1.0.3
Summary: Python wrapper for the online file sharing service file.io
Home-page: https://github.com/Chumicat/fileio_wrapper
Author: Chumicat
Author-email: russell57260620@gmail.com
License: MIT
Keywords: API wrapper,upload,download,cloud storage,file.io,file-io
Classifier: Programming Language :: Python :: 3
Classifier: License :: OSI Approved :: MIT License
Classifier: Operating System :: OS Independent
Requires-Python: >=3.6
License-File: LICENSE
Requires-Dist: requests
